phospho/__init__.py
phospho/_version.py
phospho/client.py
phospho/collection.py
phospho/config.py
phospho/consumer.py
phospho/examples/phospho_testing.py
phospho/extractor.py
phospho/integrations.py
phospho/lab/__init__.py
phospho/lab/job_library.py
phospho/lab/lab.py
phospho/lab/language_models.py
phospho/lab/models.py
phospho/lab/utils.py
phospho/log_queue.py
phospho/main.py
phospho/models.py
phospho/py.typed
phospho/sessions.py
phospho/tasks.py
phospho/testing.py
phospho/tracing.py
phospho/utils.py
phospho-0.3.45.dist-info/LICENCE
phospho-0.3.45.dist-info/METADATA
phospho-0.3.45.dist-info/WHEEL
phospho-0.3.45.dist-info/entry_points.txt
phospho-0.3.45.dist-info/RECORD
